logitech_presenter/__init__.py
logitech_presenter-1.0.1.dist-info/LICENSE
logitech_presenter-1.0.1.dist-info/WHEEL
logitech_presenter-1.0.1.dist-info/METADATA
logitech_presenter-1.0.1.dist-info/RECORD
